{
  "tb": {
    "url": "https://figshare.com/ndownloader/files/42494211",
    "version": "20230928"
  },
  "staph": {
    "url": "https://ndownloader.figshare.com/files/24914930",
    "version": "20201001"
  },
  "sonnei": {
    "url": "https://ndownloader.figshare.com/files/26274424",
    "version": "20210201"
  },
  "typhi": {
    "url": "https://figshare.com/ndownloader/files/49527246",
    "version": "20240407"
  },
  "paratyphiB": {
    "url": "https://figshare.com/ndownloader/files/43870968",
    "version": "20230627"
  }
}
